{
  "lastUpdated": "See in Repo",
  "maintainers": ["cmu community"],
  "machines": [
    {
      "id": "gh-3f",
      "name": "Gates Hillman 3rd Floor",
      "building": "Gates Hillman Complex",
      "floor": "3rd floor",
      "type": "snack",
      "lat": 40.44337131961595,
      "lng": -79.94448181432963,
      "status": "operational",
      "hours": "24/7",
      "notes": "-"
    },
    {
      "id": "gh-6f",
      "name": "Gates Hillman 6th fl",
      "building": "Gates Hillman Complex",
      "floor": "6th fl",
      "type": "snack",
      "lat": 40.44337131961595,
      "lng": -79.94448181432963,
      "status": "operational",
      "hours": "24/7",
      "notes": "Coffee and cold drinks"
    },
    {
      "id": "weh-2f",
      "name": "Wean Hall Fl 2",
      "building": "Wean Hall",
      "floor": "2nd floor, near elevators",
      "type": "combo",
      "lat": 40.4426663682563,
      "lng": -79.94589236425514,
      "status": "operational",
      "hours": "24/7"
    },
    {
      "id": "weh-7f",
      "name": "Wean Hall 7th Floor",
      "building": "Wean Hall",
      "floor": "7th floor, close to physics lounge",
      "type": "snack",
      "lat": 40.4426663682563,
      "lng": -79.94589236425514,
      "status": "limited",
      "hours": "24/7",
      "notes": "-"
    },
    {
      "id": "uc-main",
      "name": "UC Lower Level",
      "building": "University Center",
      "floor": "Lower level, Andy's Alcove",
      "type": "combo",
      "lat": 40.44344936235863,
      "lng": -79.9421305040206,
      "status": "operational",
      "hours": "-"
    },
    {
      "id": "doherty-a-east",
      "name": "Doherty Hall A level - east stairs",
      "building": "Doherty Hall",
      "floor": "A level",
      "type": "drink",
      "lat": 40.44236523500048,
      "lng": -79.94449656072504,
      "status": "operational",
      "hours": "24/7"
    },
    {
      "id": "doherty-a-middle",
      "name": "Doherty Hall A level - middle stairs",
      "building": "Doherty Hall",
      "floor": "A level",
      "type": "combo",
      "lat": 40.44236523500048,
      "lng": -79.94449656072504,
      "status": "unknown",
      "hours": "Unknown",
      "notes": "-"
    },
    {
      "id": "hbh-a-west",
      "name": "Hamburg Hall A level - west (dew)",
      "building": "Hamburg Hall",
      "floor": "A level",
      "type": "drink",
      "lat": 40.44427806341684,
      "lng": -79.94555220649606,
      "status": "operational",
      "hours": "-"
    },
        {
      "id": "hbh-a-center",
      "name": "Hamburg Hall A level - center (coffee)",
      "building": "Hamburg Hall",
      "floor": "A level",
      "type": "drink",
      "lat": 40.44427806341684,
      "lng": -79.94555220649606,
      "status": "operational",
      "hours": "-"
    },
        {
      "id": "hbh-a-center",
      "name": "Hamburg Hall A level - east (main)",
      "building": "Hamburg Hall",
      "floor": "A level",
      "type": "drink",
      "lat": 40.44427806341684,
      "lng": -79.94555220649606,
      "status": "operational",
      "hours": "-"
    },
    {
      "id": "cyert-a",
      "name": "Cyert Hall A level - Forbes entrance",
      "building": "Cyert Hall",
      "floor": "A level",
      "type": "combo",
      "lat": 40.444415465838354,
      "lng": -79.94372343127861,
      "status": "operational",
      "hours": "24/7",
      "notes": "-"
    },
    {
      "id": "nsh-1",
      "name": "Newell-Simon Hall 1",
      "building": "Newell-Simon Hall",
      "floor": "1st Fl",
      "type": "combo",
      "lat": 40.4434,
      "lng": -79.9460,
      "status": "operational",
      "hours": "24/7"
    },
    {
      "id": "tepper-1f",
      "name": "Tepper 1st Floor",
      "building": "Tepper School of Business",
      "floor": "1st",
      "type": "combo",
      "lat": 40.44490282044111,
      "lng": -79.94547912834445,
      "status": "operational",
      "hours": "-"
    }
  ]
}
